.gitignore
.travis.yml
CHANGES.txt
CONTRIBUTORS.txt
MANIFEST.in
README.rst
bootstrap.py
buildout.cfg
setup.cfg
setup.py
travis.cfg
docs/LICENSE.GPL
docs/LICENSE.txt
src/collective/__init__.py
src/collective.languagemovefolders.egg-info/PKG-INFO
src/collective.languagemovefolders.egg-info/SOURCES.txt
src/collective.languagemovefolders.egg-info/dependency_links.txt
src/collective.languagemovefolders.egg-info/entry_points.txt
src/collective.languagemovefolders.egg-info/namespace_packages.txt
src/collective.languagemovefolders.egg-info/not-zip-safe
src/collective.languagemovefolders.egg-info/requires.txt
src/collective.languagemovefolders.egg-info/top_level.txt
src/collective/languagemovefolders/__init__.py
src/collective/languagemovefolders/configure.zcml
src/collective/languagemovefolders/setuphandlers.py
src/collective/languagemovefolders/testing.py
src/collective/languagemovefolders/utils.py
src/collective/languagemovefolders/browser/__init__.py
src/collective/languagemovefolders/browser/configure.zcml
src/collective/languagemovefolders/browser/movecontentview.pt
src/collective/languagemovefolders/browser/movecontentview.py
src/collective/languagemovefolders/profiles/default/collective.languagemovefolders_various.txt
src/collective/languagemovefolders/profiles/default/metadata.xml
src/collective/languagemovefolders/tests/__init__.py
src/collective/languagemovefolders/tests/test_move.py
src/collective/languagemovefolders/tests/test_setup.py