Metadata-Version: 1.0
Name: collective.languagemovefolders
Version: 1.1
Summary: Move Into Language Folder
Home-page: https://github.com/collective/collective.milf
Author: Benoit Suttor
Author-email: bsuttor@cirb.irisnet.be
License: gpl
Platform: UNKNOWN
Classifier: Environment :: Web Environment
Classifier: Operating System :: OS Independent
Classifier: Framework :: Zope2
Classifier: Framework :: Plone
Classifier: Framework :: Plone :: 4.2
Classifier: Framework :: Plone :: 4.3
Classifier: Programming Language :: Python
Classifier: Programming Language :: Python :: 2.6
Classifier: Programming Language :: Python :: 2.7
Classifier: Topic :: Software Development :: Libraries :: Python Modules
